AUTHORS.rst
CONTRIBUTORS.rst
none/__init__.py
none/callable.py
none/collection/__init__.py
none/collection/a.py
none/collection/i.py
none/hash/__init__.py
none/hash/cdc/__init__.py
none/hash/cdc/fastcdc.py
none/hash/tree.py
none/py.typed
none/task/__init__.py
none/task/abc.py
none/text/__init__.py
none/text/case.py
none/typeset.py
none/url.py
none-0.1.1.dist-info/LICENSE.rst
none-0.1.1.dist-info/WHEEL
none-0.1.1.dist-info/METADATA
none-0.1.1.dist-info/RECORD
