Metadata-Version: 2.1
Name: none
Version: 0.1.1
Summary: An extensive library providing additional facilities to the Python Standard Library.
Home-page: https://github.com/spack971/none
License: MIT
Keywords: extensive,additional,library,utilities,tools
Author: See AUTHORS.rst
Author-email: dev@jimmy.lt
Maintainer: Jimmy Thrasibule
Maintainer-email: dev@jimmy.lt
Requires-Python: >=3.7,<4.0
Classifier: Development Status :: 1 - Planning
Classifier: Intended Audience :: Developers
Classifier: Intended Audience :: Information Technology
Classifier: License :: OSI Approved :: MIT License
Classifier: Natural Language :: English
Classifier: Operating System :: POSIX
Classifier: Programming Language :: Python
Classifier: Programming Language :: Python :: 3
Classifier: Programming Language :: Python :: 3 :: Only
Classifier: Programming Language :: Python :: 3.10
Classifier: Programming Language :: Python :: 3.7
Classifier: Programming Language :: Python :: 3.8
Classifier: Programming Language :: Python :: 3.9
Classifier: Topic :: Software Development :: Libraries
Classifier: Topic :: Software Development :: Libraries :: Python Modules
Classifier: Topic :: Utilities
Classifier: Typing :: Typed
Requires-Dist: rfc3986[url] (>=2.0.0,<3.0.0)
Requires-Dist: sphinx[docs] (>=5.1.0,<6.0.0)
Project-URL: Repository, https://github.com/spack971/none
